<?xml version="1.0" encoding="UTF-8" ?>
<!DOCTYPE struts PUBLIC
    "-//Apache Software Foundation//DTD Struts Configuration 2.0//EN"
    "http://struts.apache.org/dtds/struts-2.0.dtd">
<struts>
	<package name="crm-default" extends="framework-default">
		<global-results>
    		<result name="jspError">${referer}</result>
    		<result name="jsonError" type="jsonerror"></result>
    		<result name="jspLogin" type="redirect">login.action</result>
    		<result name="jsonLogin" type="jsonerror"></result>
    	</global-results>
	</package>
</struts>